py_grpcio/__init__.py
py_grpcio/__meta__.py
py_grpcio/enums.py
py_grpcio/exceptions.py
py_grpcio/interceptor.py
py_grpcio/method.py
py_grpcio/middleware.py
py_grpcio/models.py
py_grpcio/proto/__init__.py
py_grpcio/proto/enums.py
py_grpcio/proto/parser.py
py_grpcio/proto/templates/service.proto.jinja2
py_grpcio/server/__init__.py
py_grpcio/server/base.py
py_grpcio/service/__init__.py
py_grpcio/service/base.py
py_grpcio/service/meta.py
py_grpcio/utils.py
py_grpcio-1.8.1.dist-info/LICENSE
py_grpcio-1.8.1.dist-info/METADATA
py_grpcio-1.8.1.dist-info/WHEEL
py_grpcio-1.8.1.dist-info/RECORD
