Metadata-Version: 2.3
Name: py-grpcio
Version: 1.8.1
Summary: gRPC with autogen by Pydantic models
License: MIT
Author: Yurii
Author-email: ykolibroda@lytvynov-production.com
Requires-Python: >=3.12,<4.0
Classifier: License :: OSI Approved :: MIT License
Classifier: Programming Language :: Python :: 3
Classifier: Programming Language :: Python :: 3.12
Classifier: Programming Language :: Python :: 3.13
Requires-Dist: grpc-interceptor (>=0.15.4,<0.16.0)
Requires-Dist: grpcio (>=1.71.0,<2.0.0)
Requires-Dist: grpcio-tools (>=1.71.0,<2.0.0)
Requires-Dist: jinja2 (>=3.1.3,<4.0.0)
Requires-Dist: loguru (>=0.7.2,<0.8.0)
Requires-Dist: pydantic (<3.0.0)
